{
  "$description": "White preset — Clean white surfaces",
  "light": {
    "surface": {
      "0": {
        "$value": "0.962 0 0",
        "$type": "color"
      },
      "1": {
        "$value": "1 0 0",
        "$type": "color"
      },
      "2": {
        "$value": "0.97 0 0",
        "$type": "color"
      },
      "3": {
        "$value": "1 0 0",
        "$type": "color"
      },
      "4": {
        "$value": "0.985 0.003 0",
        "$type": "color"
      },
      "0-hover": {
        "$value": "0.939 0 0",
        "$type": "color"
      },
      "0-active": {
        "$value": "0.916 0 0",
        "$type": "color"
      },
      "0-highlight": {
        "$value": "0.931 0 0",
        "$type": "color"
      },
      "1-hover": {
        "$value": "0.977 0 0",
        "$type": "color"
      },
      "1-active": {
        "$value": "0.954 0 0",
        "$type": "color"
      },
      "1-highlight": {
        "$value": "0.97 0 0",
        "$type": "color"
      },
      "2-hover": {
        "$value": "0.97 0 0",
        "$type": "color"
      },
      "2-active": {
        "$value": "0.947 0 0",
        "$type": "color"
      },
      "2-highlight": {
        "$value": "0.962 0 0",
        "$type": "color"
      },
      "3-hover": {
        "$value": "0.977 0 0",
        "$type": "color"
      },
      "3-active": {
        "$value": "0.954 0 0",
        "$type": "color"
      },
      "3-highlight": {
        "$value": "0.97 0 0",
        "$type": "color"
      },
      "4-hover": {
        "$value": "0.965 0.004 0",
        "$type": "color"
      },
      "4-active": {
        "$value": "0.945 0.005 0",
        "$type": "color"
      },
      "4-highlight": {
        "$value": "0.96 0.006 0",
        "$type": "color"
      }
    },
    "border": {
      "subtle": {
        "$value": "0.908 0 0",
        "$type": "color"
      },
      "default": {
        "$value": "0.845 0 0",
        "$type": "color"
      }
    },
    "accent": {
      "default": {
        "$value": "0.97 0 0",
        "$type": "color"
      },
      "foreground": {
        "$value": "0.204 0 0",
        "$type": "color"
      },
      "hover": {
        "$value": "0.923 0 0",
        "$type": "color"
      }
    },
    "sidebar": {
      "accent": {
        "$value": "0.97 0 0",
        "$type": "color"
      },
      "accent-foreground": {
        "$value": "0.204 0 0",
        "$type": "color"
      },
      "hover": {
        "$value": "0.962 0 0",
        "$type": "color"
      }
    },
    "tab": {
      "bg": {
        "$value": "0.947 0 0",
        "$type": "color"
      },
      "bg-hover": {
        "$value": "0.923 0 0",
        "$type": "color"
      },
      "outline": {
        "$value": "0.861 0 0",
        "$type": "color"
      }
    },
    "input": {
      "bg": {
        "$value": "1 0 0",
        "$type": "color"
      },
      "border": {
        "$value": "0.908 0 0",
        "$type": "color"
      },
      "border-hover": {
        "$value": "0.845 0 0",
        "$type": "color"
      },
      "border-focus": {
        "$value": "0.65 0.08 0",
        "$type": "color"
      },
      "border-active": {
        "$value": "0.805 0 0",
        "$type": "color"
      },
      "border-highlight": {
        "$value": "0.829 0 0",
        "$type": "color"
      },
      "bg-active": {
        "$value": "0.977 0 0",
        "$type": "color"
      },
      "bg-highlight": {
        "$value": "0.985 0 0",
        "$type": "color"
      },
      "bg-disabled": {
        "$value": "0.97 0 0",
        "$type": "color"
      },
      "placeholder": {
        "$value": "0.649 0 0",
        "$type": "color"
      }
    },
    "background": {
      "$value": "0.962 0 0",
      "$type": "color"
    },
    "panel-background": {
      "$value": "1 0 0",
      "$type": "color"
    },
    "main-panel-background": {
      "$value": "1 0 0",
      "$type": "color"
    }
  },
  "surfaceScopes": {
    "light": {
      "0": {
        "input": {
          "bg": {
            "$value": "1 0 0",
            "$type": "color"
          },
          "border": {
            "$value": "0.892 0 0",
            "$type": "color"
          },
          "border-hover": {
            "$value": "0.829 0 0",
            "$type": "color"
          },
          "border-focus": {
            "$value": "0.829 0 0",
            "$type": "color"
          },
          "border-error": {
            "$value": "0.636 0.2082 25.4",
            "$type": "color"
          },
          "border-active": {
            "$value": "0.789 0 0",
            "$type": "color"
          },
          "border-highlight": {
            "$value": "0.813 0 0",
            "$type": "color"
          },
          "bg-active": {
            "$value": "0.977 0 0",
            "$type": "color"
          },
          "bg-highlight": {
            "$value": "0.985 0 0",
            "$type": "color"
          },
          "bg-disabled": {
            "$value": "0.962 0 0",
            "$type": "color"
          },
          "placeholder": {
            "$value": "0.649 0 0",
            "$type": "color"
          }
        },
        "tab": {
          "bg": {
            "$value": "0.931 0 0",
            "$type": "color"
          },
          "bg-hover": {
            "$value": "0.908 0 0",
            "$type": "color"
          },
          "outline": {
            "$value": "0.845 0 0",
            "$type": "color"
          }
        },
        "border": {
          "subtle": {
            "$value": "0.9 0 0",
            "$type": "color"
          },
          "default": {
            "$value": "0.837 0 0",
            "$type": "color"
          }
        }
      },
      "1": {
        "input": {
          "bg": {
            "$value": "0.97 0 0",
            "$type": "color"
          },
          "border": {
            "$value": "0.885 0 0",
            "$type": "color"
          },
          "border-hover": {
            "$value": "0.829 0 0",
            "$type": "color"
          },
          "border-focus": {
            "$value": "0.829 0 0",
            "$type": "color"
          },
          "border-error": {
            "$value": "0.636 0.2082 25.4",
            "$type": "color"
          },
          "border-active": {
            "$value": "0.789 0 0",
            "$type": "color"
          },
          "border-highlight": {
            "$value": "0.813 0 0",
            "$type": "color"
          },
          "bg-active": {
            "$value": "0.947 0 0",
            "$type": "color"
          },
          "bg-highlight": {
            "$value": "0.954 0 0",
            "$type": "color"
          },
          "bg-disabled": {
            "$value": "0.947 0 0",
            "$type": "color"
          },
          "placeholder": {
            "$value": "0.649 0 0",
            "$type": "color"
          }
        },
        "tab": {
          "bg": {
            "$value": "0.954 0 0",
            "$type": "color"
          },
          "bg-hover": {
            "$value": "0.931 0 0",
            "$type": "color"
          },
          "outline": {
            "$value": "0.845 0 0",
            "$type": "color"
          }
        },
        "border": {
          "subtle": {
            "$value": "0.892 0 0",
            "$type": "color"
          },
          "default": {
            "$value": "0.829 0 0",
            "$type": "color"
          }
        }
      },
      "2": {
        "input": {
          "bg": {
            "$value": "0.992 0 0",
            "$type": "color"
          },
          "border": {
            "$value": "0.885 0 0",
            "$type": "color"
          },
          "border-hover": {
            "$value": "0.829 0 0",
            "$type": "color"
          },
          "border-focus": {
            "$value": "0.829 0 0",
            "$type": "color"
          },
          "border-error": {
            "$value": "0.636 0.2082 25.4",
            "$type": "color"
          },
          "border-active": {
            "$value": "0.789 0 0",
            "$type": "color"
          },
          "border-highlight": {
            "$value": "0.813 0 0",
            "$type": "color"
          },
          "bg-active": {
            "$value": "0.97 0 0",
            "$type": "color"
          },
          "bg-highlight": {
            "$value": "0.977 0 0",
            "$type": "color"
          },
          "bg-disabled": {
            "$value": "0.954 0 0",
            "$type": "color"
          },
          "placeholder": {
            "$value": "0.649 0 0",
            "$type": "color"
          }
        },
        "tab": {
          "bg": {
            "$value": "0.947 0 0",
            "$type": "color"
          },
          "bg-hover": {
            "$value": "0.923 0 0",
            "$type": "color"
          },
          "outline": {
            "$value": "0.845 0 0",
            "$type": "color"
          }
        },
        "border": {
          "subtle": {
            "$value": "0.892 0 0",
            "$type": "color"
          },
          "default": {
            "$value": "0.829 0 0",
            "$type": "color"
          }
        }
      },
      "3": {
        "input": {
          "bg": {
            "$value": "0.97 0 0",
            "$type": "color"
          },
          "border": {
            "$value": "0.885 0 0",
            "$type": "color"
          },
          "border-hover": {
            "$value": "0.829 0 0",
            "$type": "color"
          },
          "border-focus": {
            "$value": "0.829 0 0",
            "$type": "color"
          },
          "border-error": {
            "$value": "0.636 0.2082 25.4",
            "$type": "color"
          },
          "border-active": {
            "$value": "0.789 0 0",
            "$type": "color"
          },
          "border-highlight": {
            "$value": "0.813 0 0",
            "$type": "color"
          },
          "bg-active": {
            "$value": "0.947 0 0",
            "$type": "color"
          },
          "bg-highlight": {
            "$value": "0.954 0 0",
            "$type": "color"
          },
          "bg-disabled": {
            "$value": "0.947 0 0",
            "$type": "color"
          },
          "placeholder": {
            "$value": "0.649 0 0",
            "$type": "color"
          }
        },
        "tab": {
          "bg": {
            "$value": "0.954 0 0",
            "$type": "color"
          },
          "bg-hover": {
            "$value": "0.931 0 0",
            "$type": "color"
          },
          "outline": {
            "$value": "0.845 0 0",
            "$type": "color"
          }
        },
        "border": {
          "subtle": {
            "$value": "0.892 0 0",
            "$type": "color"
          },
          "default": {
            "$value": "0.829 0 0",
            "$type": "color"
          }
        }
      },
      "4": {
        "input": {
          "bg": {
            "$value": "0.97 0 0",
            "$type": "color"
          },
          "border": {
            "$value": "0.885 0 0",
            "$type": "color"
          },
          "border-hover": {
            "$value": "0.829 0 0",
            "$type": "color"
          },
          "border-focus": {
            "$value": "0.829 0 0",
            "$type": "color"
          },
          "border-error": {
            "$value": "0.636 0.2082 25.4",
            "$type": "color"
          },
          "border-active": {
            "$value": "0.789 0 0",
            "$type": "color"
          },
          "border-highlight": {
            "$value": "0.813 0 0",
            "$type": "color"
          },
          "bg-active": {
            "$value": "0.947 0 0",
            "$type": "color"
          },
          "bg-highlight": {
            "$value": "0.954 0 0",
            "$type": "color"
          },
          "bg-disabled": {
            "$value": "0.947 0 0",
            "$type": "color"
          },
          "placeholder": {
            "$value": "0.649 0 0",
            "$type": "color"
          }
        },
        "tab": {
          "bg": {
            "$value": "0.954 0 0",
            "$type": "color"
          },
          "bg-hover": {
            "$value": "0.931 0 0",
            "$type": "color"
          },
          "outline": {
            "$value": "0.845 0 0",
            "$type": "color"
          }
        },
        "border": {
          "subtle": {
            "$value": "0.892 0 0",
            "$type": "color"
          },
          "default": {
            "$value": "0.829 0 0",
            "$type": "color"
          }
        }
      }
    }
  }
}
